azure_cli_datalake-0.0.1b2-py3.5-nspkg.pth
azure/cli/command_modules/datalake/__init__.py
azure/cli/command_modules/datalake/analytics/__init__.py
azure/cli/command_modules/datalake/analytics/_client_factory.py
azure/cli/command_modules/datalake/analytics/_help.py
azure/cli/command_modules/datalake/analytics/_params.py
azure/cli/command_modules/datalake/analytics/_validators.py
azure/cli/command_modules/datalake/analytics/commands.py
azure/cli/command_modules/datalake/analytics/custom.py
azure/cli/command_modules/datalake/store/__init__.py
azure/cli/command_modules/datalake/store/_client_factory.py
azure/cli/command_modules/datalake/store/_help.py
azure/cli/command_modules/datalake/store/_params.py
azure/cli/command_modules/datalake/store/_validators.py
azure/cli/command_modules/datalake/store/commands.py
azure/cli/command_modules/datalake/store/custom.py
azure_cli_datalake-0.0.1b2.dist-info/DESCRIPTION.rst
azure_cli_datalake-0.0.1b2.dist-info/METADATA
azure_cli_datalake-0.0.1b2.dist-info/RECORD
azure_cli_datalake-0.0.1b2.dist-info/WHEEL
azure_cli_datalake-0.0.1b2.dist-info/metadata.json
azure_cli_datalake-0.0.1b2.dist-info/namespace_packages.txt
azure_cli_datalake-0.0.1b2.dist-info/top_level.txt
