Metadata-Version: 2.0
Name: azure-cli-datalake
Version: 0.0.1b2
Summary: Microsoft Azure Command-Line Tools Data Lake Command Module
Home-page: https://github.com/Azure/azure-cli
Author: Microsoft Corporation
Author-email: azpycli@microsoft.com
License: MIT
Platform: UNKNOWN
Classifier: Development Status :: 4 - Beta
Classifier: Intended Audience :: Developers
Classifier: Intended Audience :: System Administrators
Classifier: Programming Language :: Python
Classifier: Programming Language :: Python :: 2
Classifier: Programming Language :: Python :: 2.7
Classifier: Programming Language :: Python :: 3
Classifier: Programming Language :: Python :: 3.4
Classifier: Programming Language :: Python :: 3.5
Classifier: Programming Language :: Python :: 3.6
Classifier: License :: OSI Approved :: MIT License
Requires-Dist: azure-cli-core
Requires-Dist: azure-datalake-store (==0.0.5)
Requires-Dist: azure-mgmt-datalake-analytics (==0.1.3)
Requires-Dist: azure-mgmt-datalake-store (==0.1.3)
